AUTHORS
LICENSE
README.md
VERSION
callbacks
cubescape-gl
cubescape-gles
cubescape-glfw-gl
cubescape-glfw-gles
cubescape-gtk3-gl
cubescape-gtk3-gles
cubescape-log
cubescape-qt-gl
cubescape-qt-gles
cubescape-sdl-gl
cubescape-sdl-gles
glbinding-config.cmake
glbinding-glcontexts
glbinding-glescontexts
glbinding-glfunctions
glbinding-glinfo
glbinding-glisdeprecated
glbinding-glmeta
glbinding-glqueries
multi-context
cmake/FindKHR.cmake
cmake/KHRplatform/KHRplatform-export.cmake
cmake/glbinding/glbinding-export-release.cmake
cmake/glbinding/glbinding-export.cmake
cmake/glbinding-aux/glbinding-aux-export-release.cmake
cmake/glbinding-aux/glbinding-aux-export.cmake
data/cubescape/cubescape.frag
data/cubescape/cubescape.geom
data/cubescape/cubescape.vert
data/cubescape/patches.64.16.rgb.ub.raw
data/cubescape/shaderconfig.json
data/cubescape/terrain.64.64.r.ub.raw
data/cubescape-gles/cubescape.frag
data/cubescape-gles/cubescape.geom
data/cubescape-gles/cubescape.vert
data/cubescape-gles/patches.64.16.rgb.ub.raw
data/cubescape-gles/shaderconfig.json
data/cubescape-gles/terrain.64.64.r.ub.raw
include/GLFW/glfw3.h
include/GLFW/glfw3native.h
include/flatbuffers/allocator.h
include/flatbuffers/array.h
include/flatbuffers/base.h
include/flatbuffers/buffer.h
include/flatbuffers/buffer_ref.h
include/flatbuffers/code_generator.h
include/flatbuffers/code_generators.h
include/flatbuffers/default_allocator.h
include/flatbuffers/detached_buffer.h
include/flatbuffers/file_manager.h
include/flatbuffers/flatbuffer_builder.h
include/flatbuffers/flatbuffers.h
include/flatbuffers/flatc.h
include/flatbuffers/flex_flat_util.h
include/flatbuffers/flexbuffers.h
include/flatbuffers/grpc.h
include/flatbuffers/hash.h
include/flatbuffers/idl.h
include/flatbuffers/minireflect.h
include/flatbuffers/reflection.h
include/flatbuffers/reflection_generated.h
include/flatbuffers/registry.h
include/flatbuffers/stl_emulation.h
slamd-2.1.12.dist-info/METADATA
slamd-2.1.12.dist-info/WHEEL
slamd-2.1.12.dist-info/entry_points.txt
slamd-2.1.12.dist-info/RECORD
