Metadata-Version: 2.1
Name: slamd
Version: 2.1.12
Summary: Python bindings for SlamDunk
Author-Email: Robert Leo <robert.leo.jonsson@gmail.com>
Requires-Python: >=3.11
Requires-Dist: numpy>=1.23
